{
  "Commands": [
    {
      "SemanticQueryDataShapeCommand": {
        "Query": {
          "Version": 2,
          "From": [
            {
              "Name": "f",
              "Entity": "Fact",
              "Type": 0
            },
            {
              "Name": "d",
              "Entity": "Date",
              "Type": 0
            },
            {
              "Name": "e",
              "Entity": "Executive",
              "Type": 0
            },
            {
              "Name": "i",
              "Entity": "Industry",
              "Type": 0
            }
          ],
          "Select": [
            {
              "Measure": {
                "Expression": {
                  "SourceRef": {
                    "Source": "f"
                  }
                },
                "Property": "# of Customers"
              },
              "Name": "Fact.# of Customers"
            }
          ],
          "Where": [
            {
              "Condition": {
                "Comparison": {
                  "ComparisonKind": 0,
                  "Left": {
                    "Column": {
                      "Expression": {
                        "SourceRef": {
                          "Source": "d"
                        }
                      },
                      "Property": "Year"
                    }
                  },
                  "Right": {
                    "Literal": {
                      "Value": "2014L"
                    }
                  }
                }
              }
            },
            {
              "Condition": {
                "Not": {
                  "Expression": {
                    "Or": {
                      "Left": {
                        "Or": {
                          "Left": {
                            "Or": {
                              "Left": {
                                "Comparison": {
                                  "ComparisonKind": 0,
                                  "Left": {
                                    "Column": {
                                      "Expression": {
                                        "SourceRef": {
                                          "Source": "e"
                                        }
                                      },
                                      "Property": "ID"
                                    }
                                  },
                                  "Right": {
                                    "Literal": {
                                      "Value": "6L"
                                    }
                                  }
                                }
                              },
                              "Right": {
                                "Comparison": {
                                  "ComparisonKind": 0,
                                  "Left": {
                                    "Column": {
                                      "Expression": {
                                        "SourceRef": {
                                          "Source": "e"
                                        }
                                      },
                                      "Property": "ID"
                                    }
                                  },
                                  "Right": {
                                    "Literal": {
                                      "Value": "10L"
                                    }
                                  }
                                }
                              }
                            }
                          },
                          "Right": {
                            "Comparison": {
                              "ComparisonKind": 0,
                              "Left": {
                                "Column": {
                                  "Expression": {
                                    "SourceRef": {
                                      "Source": "e"
                                    }
                                  },
                                  "Property": "ID"
                                }
                              },
                              "Right": {
                                "Literal": {
                                  "Value": "9L"
                                }
                              }
                            }
                          }
                        }
                      },
                      "Right": {
                        "Comparison": {
                          "ComparisonKind": 0,
                          "Left": {
                            "Column": {
                              "Expression": {
                                "SourceRef": {
                                  "Source": "e"
                                }
                              },
                              "Property": "ID"
                            }
                          },
                          "Right": {
                            "Literal": {
                              "Value": "7L"
                            }
                          }
                        }
                      }
                    }
                  }
                }
              }
            },
            {
              "Condition": {
                "Not": {
                  "Expression": {
                    "In": {
                      "Expressions": [
                        {
                          "Column": {
                            "Expression": {
                              "SourceRef": {
                                "Source": "i"
                              }
                            },
                            "Property": "ID"
                          }
                        }
                      ],
                      "Values": [
                        [
                          {
                            "Literal": {
                              "Value": "12L"
                            }
                          }
                        ],
                        [
                          {
                            "Literal": {
                              "Value": "16L"
                            }
                          }
                        ],
                        [
                          {
                            "Literal": {
                              "Value": "17L"
                            }
                          }
                        ],
                        [
                          {
                            "Literal": {
                              "Value": "29L"
                            }
                          }
                        ]
                      ]
                    }
                  }
                }
              }
            }
          ]
        },
        "Binding": {
          "Primary": {
            "Groupings": [
              {
                "Projections": [
                  0
                ]
              }
            ]
          },
          "DataReduction": {
            "DataVolume": 3,
            "Primary": {
              "Top": {}
            }
          },
          "Version": 1
        },
        "ExecutionMetricsKind": 1
      }
    }
  ]
}